authipy/__init__.py
authipy/main.py
authipy/version.py
authipy-0.0.4.dist-info/licenses/LICENSE
authipy-0.0.4.dist-info/METADATA
authipy-0.0.4.dist-info/WHEEL
authipy-0.0.4.dist-info/entry_points.txt
authipy-0.0.4.dist-info/top_level.txt
authipy-0.0.4.dist-info/RECORD
