Metadata-Version: 2.4
Name: Authipy
Version: 0.0.4
Summary: 2FA Authenticator
Home-page: https://github.com/TanmoyTheBoT/Authipy
Author: TanmoyTheBoT
Classifier: Programming Language :: Python :: 3
Classifier: License :: OSI Approved :: MIT License
Classifier: Operating System :: OS Independent
Requires-Python: >=3.8
License-File: LICENSE
Requires-Dist: PyQt5>=5.15.0
Requires-Dist: pyotp>=2.8.0
Requires-Dist: pyperclip>=1.8.2
Requires-Dist: PyQRCode>=1.2.1
Requires-Dist: pypng>=0.20220715.0
Dynamic: author
Dynamic: classifier
Dynamic: description
Dynamic: description-content-type
Dynamic: home-page
Dynamic: license-file
Dynamic: requires-dist
Dynamic: requires-python
Dynamic: summary
